{
    "version": "0.2.19",
    "architecture": {
        "64bit": {
            "url": "https://github.com/blitui/blit/releases/download/v0.2.19/blit_0.2.19_windows_amd64.zip",
            "bin": [
                "blit.exe"
            ],
            "hash": "68ea31a8756da84f9e2517349cc8d0df42aebe692a015c5f5123c7e6a4425fab"
        },
        "arm64": {
            "url": "https://github.com/blitui/blit/releases/download/v0.2.19/blit_0.2.19_windows_arm64.zip",
            "bin": [
                "blit.exe"
            ],
            "hash": "a0853c4af4d2916167d7d21cd910ca8289d3401271953ffddf49d0e8ccd5e63d"
        }
    },
    "homepage": "https://github.com/blitui/blit",
    "license": "MIT",
    "description": "CLI for blit — the pragmatic Go TUI toolkit"
}
